pyrotoolbox/HtmlReporter.py
pyrotoolbox/__init__.py
pyrotoolbox/oxycalc.dll
pyrotoolbox/oxycalc.so
pyrotoolbox/oxygen.py
pyrotoolbox/pH.py
pyrotoolbox/parsers.py
pyrotoolbox/phase.py
pyrotoolbox/FireResponse/FireResponse.py
pyrotoolbox/FireResponse/__init__.py
pyrotoolbox-1.12b0.dist-info/METADATA
pyrotoolbox-1.12b0.dist-info/WHEEL
pyrotoolbox-1.12b0.dist-info/entry_points.txt
pyrotoolbox-1.12b0.dist-info/licenses/LICENSE
pyrotoolbox-1.12b0.dist-info/RECORD
