Metadata-Version: 2.4
Name: pyrotoolbox
Version: 1.12b0
Project-URL: Homepage, https://github.com/PyroScience-GmbH/pyrotoolbox
Project-URL: Documentation, https://pyrotoolbox.readthedocs.io/en/latest/
Author-email: Christoph Staudinger <cs@pyroscience.com>
License-File: LICENSE
Requires-Python: >=3.10
Requires-Dist: lmfit
Requires-Dist: numpy
Requires-Dist: pandas
Requires-Dist: plotly
Provides-Extra: fireresponse
Requires-Dist: pyqt5; extra == 'fireresponse'
Requires-Dist: pyqtgraph; extra == 'fireresponse'
